spakky/plugins/security/__init__.py
spakky/plugins/security/cryptography/__init__.py
spakky/plugins/security/cryptography/aes.py
spakky/plugins/security/cryptography/gcm.py
spakky/plugins/security/cryptography/interface.py
spakky/plugins/security/cryptography/rsa.py
spakky/plugins/security/encoding.py
spakky/plugins/security/error.py
spakky/plugins/security/hash.py
spakky/plugins/security/hmac_signer.py
spakky/plugins/security/jwt.py
spakky/plugins/security/key.py
spakky/plugins/security/main.py
spakky/plugins/security/password/__init__.py
spakky/plugins/security/password/argon2.py
spakky/plugins/security/password/bcrypt.py
spakky/plugins/security/password/interface.py
spakky/plugins/security/password/pbkdf2.py
spakky/plugins/security/password/scrypt.py
spakky/plugins/security/py.typed
spakky_security-5.0.1.dist-info/WHEEL
spakky_security-5.0.1.dist-info/entry_points.txt
spakky_security-5.0.1.dist-info/METADATA
spakky_security-5.0.1.dist-info/RECORD
