Metadata-Version: 2.3
Name: spakky-security
Version: 5.0.1
Summary: Security utilities plugin for Spakky framework
Author: Spakky
Author-email: Spakky <sejong418@icloud.com>
License: MIT
Requires-Dist: argon2-cffi>=25.1.0
Requires-Dist: bcrypt>=5.0.0
Requires-Dist: pycryptodome>=3.23.0
Requires-Dist: spakky>=5.0.1
Requires-Python: >=3.11
